{
  "name": "poe-ui",
  "repo": "poegroup/poe-ui",
  "description": "high-productivity collection of tools and practices for rapidly writing production-ready applications",
  "version": "0.4.7",
  "keywords": [],
  "dependencies": {
    "camshaft/access-token": "*",
    "camshaft/envs": "*",
    "camshaft/metric-log": "*",
    "camshaft/log": "*",
    "camshaft/ng-feature": "*",
    "camshaft/feature-ui": "*",
    "hypergroup/ng-hyper": "^0.1.2",
    "hypergroup/ng-hyper-translate": "*",
    "ianstormtaylor/to-camel-case": "^0.2.1"
  },
  "development": {},
  "license": "MIT",
  "main": "client.js",
  "scripts": [
    "client.js",
    "client/logger.js"
  ],
  "remotes": []
}
